AeroMix/AeroMix_main.py
AeroMix/CopyAerosolData.py
AeroMix/__init__.py
AeroMix/getAerosolType.py
AeroMix/newAerosol.py
AeroMix/aerosol_components/BC00
AeroMix/aerosol_components/IS00
AeroMix/aerosol_components/MDam00
AeroMix/aerosol_components/MDcm00
AeroMix/aerosol_components/MDnm00
AeroMix/aerosol_components/SSam00
AeroMix/aerosol_components/SSam50
AeroMix/aerosol_components/SSam70
AeroMix/aerosol_components/SSam80
AeroMix/aerosol_components/SSam90
AeroMix/aerosol_components/SSam95
AeroMix/aerosol_components/SSam98
AeroMix/aerosol_components/SSam99
AeroMix/aerosol_components/SScm00
AeroMix/aerosol_components/SScm50
AeroMix/aerosol_components/SScm70
AeroMix/aerosol_components/SScm80
AeroMix/aerosol_components/SScm90
AeroMix/aerosol_components/SScm95
AeroMix/aerosol_components/SScm98
AeroMix/aerosol_components/SScm99
AeroMix/aerosol_components/SUSO00
AeroMix/aerosol_components/SUSO50
AeroMix/aerosol_components/SUSO70
AeroMix/aerosol_components/SUSO80
AeroMix/aerosol_components/SUSO90
AeroMix/aerosol_components/SUSO95
AeroMix/aerosol_components/SUSO98
AeroMix/aerosol_components/SUSO99
AeroMix/aerosol_components/WS00
AeroMix/aerosol_components/WS50
AeroMix/aerosol_components/WS70
AeroMix/aerosol_components/WS80
AeroMix/aerosol_components/WS90
AeroMix/aerosol_components/WS95
AeroMix/aerosol_components/WS98
AeroMix/aerosol_components/WS99
AeroMix-1.0.1.dist-info/LICENCE
AeroMix-1.0.1.dist-info/METADATA
AeroMix-1.0.1.dist-info/WHEEL
AeroMix-1.0.1.dist-info/top_level.txt
AeroMix-1.0.1.dist-info/RECORD
