Metadata-Version: 2.1
Name: AeroMix
Version: 1.0.1
Summary: Python package for modeling aerosol optical properties
Home-page: https://github.com/sampr7/AeroMix
Author: Sam P Raj
Author-email: sampr7@gmail.com
License: GNU General Public License v3 (GPLv3)
Keywords: aerosol model mixing state AOD SSA g
Classifier: Development Status :: 5 - Production/Stable
Classifier: Intended Audience :: Science/Research
Classifier: Topic :: Scientific/Engineering :: Atmospheric Science
Classifier: License :: OSI Approved :: GNU General Public License v3 (GPLv3)
Classifier: Programming Language :: Python :: 3
Classifier: Operating System :: OS Independent
License-File: LICENCE
Requires-Dist: numpy
Requires-Dist: scipy
Requires-Dist: PyMieScatt
